solar_apparent_time/__init__.py
solar_apparent_time/solar_apparent_time.py
solar_apparent_time/version.py
solar_apparent_time-1.5.4.dist-info/licenses/LICENSE
solar_apparent_time-1.5.4.dist-info/METADATA
solar_apparent_time-1.5.4.dist-info/WHEEL
solar_apparent_time-1.5.4.dist-info/top_level.txt
solar_apparent_time-1.5.4.dist-info/RECORD
