Metadata-Version: 2.4
Name: solar-apparent-time
Version: 1.5.4
Summary: methods to translate Python datetime between solar apparent time and Coordinate Universal Time (UTC)
Author-email: "Gregory H. Halverson" <gregory.h.halverson@jpl.nasa.gov>
Project-URL: Homepage, https://github.com/JPL-Evapotranspiration-Algorithms/solar-apparent-time
Classifier: Programming Language :: Python :: 3
Classifier: Operating System :: OS Independent
Requires-Python: >=3.10
License-File: LICENSE
Requires-Dist: numpy
Requires-Dist: rasters
Dynamic: license-file
